README
setup.py
pycontrol/__init__.py
pycontrol/pycontrol.py
pycontrol/utils.py
pycontrol.egg-info/PKG-INFO
pycontrol.egg-info/SOURCES.txt
pycontrol.egg-info/dependency_links.txt
pycontrol.egg-info/requires.txt
pycontrol.egg-info/top_level.txt