Metadata-Version: 1.0
Name: pycontrol
Version: 2.1
Summary: Library for F5 iControl API
Home-page: https://github.com/mcauthorn/pycontrol
Author: Matt Cauthorn
Author-email: mcauthorn@gmail.com
License: GPL
Keywords: iControl F5 API
Platform: any
Classifier: Operating System :: OS Independent
Classifier: Programming Language :: Python
